t_prompts/__init__.py
t_prompts/diff.py
t_prompts/element.py
t_prompts/exceptions.py
t_prompts/ir.py
t_prompts/parsing.py
t_prompts/py.typed
t_prompts/source_location.py
t_prompts/structured_prompt.py
t_prompts/text.py
t_prompts/widgets/__init__.py
t_prompts/widgets/config.py
t_prompts/widgets/export.py
t_prompts/widgets/index.js
t_prompts/widgets/preview.py
t_prompts/widgets/renderer.py
t_prompts/widgets/utils.py
t_prompts/widgets/widget.py
t_prompts/widgets/demos/__init__.py
t_prompts/widgets/demos/demo_00.py
t_prompts/widgets/demos/demo_01.py
t_prompts/widgets/demos/demo_03.py
t_prompts/widgets/demos/demo_04.py
t_prompts/widgets/demos/demo_rendered_diff.py
t_prompts/widgets/demos/demo_rendered_diff_size_metrics.py
t_prompts/widgets/demos/demo_screenshot.py
t_prompts/widgets/demos/demo_structured_diff.py
t_prompts/widgets/demos/demo_structured_diff_size_metrics.py
t_prompts-0.18.1.dist-info/METADATA
t_prompts-0.18.1.dist-info/WHEEL
t_prompts-0.18.1.dist-info/licenses/LICENSE
t_prompts-0.18.1.dist-info/RECORD
