Metadata-Version: 2.4
Name: t-prompts
Version: 0.18.1
Summary: Structured prompts using template strings
Project-URL: Homepage, https://github.com/habemus-papadum/t-prompts
Project-URL: Repository, https://github.com/habemus-papadum/t-prompts
Project-URL: Documentation, https://github.com/habemus-papadum/t-prompts
Author-email: Nehal Patel <nehal@alum.mit.edu>
License: MIT License
License-File: LICENSE
Classifier: Intended Audience :: Developers
Classifier: License :: OSI Approved :: MIT License
Classifier: Operating System :: OS Independent
Classifier: Programming Language :: Python :: 3
Classifier: Topic :: Software Development :: Libraries
Classifier: Topic :: Software Development :: Libraries :: Python Modules
Requires-Python: >=3.14
Requires-Dist: pillow>=10.0.0
Requires-Dist: pytest-cov>=7.0.0
